elisp/semantics.py
elisp/__init__.py
elisp/types.py
elisp/parser.py
elisp/compat.py
elisp-0.5.dist-info/WHEEL
elisp-0.5.dist-info/metadata.json
elisp-0.5.dist-info/RECORD
elisp-0.5.dist-info/DESCRIPTION.rst
elisp-0.5.dist-info/top_level.txt
elisp-0.5.dist-info/METADATA
