Metadata-Version: 2.0
Name: elisp
Version: 0.5
Summary: Emacs Lisp parser
Home-page: https://github.com/jorgenschaefer/elisp
Author: Jorgen Schaefer
Author-email: contact@jorgenschaefer.de
License: LGPL
Platform: UNKNOWN
Classifier: Development Status :: 5 - Production/Stable
Classifier: Intended Audience :: Developers
Classifier: Natural Language :: English
Classifier: Programming Language :: Emacs-Lisp
Classifier: License :: OSI Approved :: GNU Lesser General Public License v3 or later (LGPLv3+)
Requires-Dist: grako
